torch_images/__init__.py
torch_images/unlabled_image_dataset.py
torch_images-0.1.1.dist-info/WHEEL
torch_images-0.1.1.dist-info/METADATA
torch_images-0.1.1.dist-info/RECORD
