Metadata-Version: 2.1
Name: torch-images
Version: 0.1.1
Summary: 
License: MIT
Author: yohan-pg
Author-email: pg.yohan@gmail.com
Requires-Python: >=3.7,<4.0
Classifier: License :: OSI Approved :: MIT License
Classifier: Programming Language :: Python :: 3
Classifier: Programming Language :: Python :: 3.7
Classifier: Programming Language :: Python :: 3.8
Classifier: Programming Language :: Python :: 3.9
Requires-Dist: torch (>=1.11.0,<2.0.0)
